{"stats":{"minecraft:mined":{"minecraft:black_bed":2},"minecraft:crafted":{"minecraft:scute":1,"minecraft:damaged_anvil":1,"minecraft:iron_door":1},"minecraft:used":{"minecraft:turtle_spawn_egg":4,"minecraft:oak_fence":3,"minecraft:purpur_block":1,"minecraft:dark_oak_stairs":24,"minecraft:water_bucket":53,"minecraft:end_rod":56,"minecraft:birch_planks":291,"minecraft:dark_oak_sign":1,"minecraft:ladder":29,"minecraft:black_carpet":11,"minecraft:spruce_planks":32,"minecraft:quartz_stairs":5,"minecraft:green_bed":1,"minecraft:cookie":4,"minecraft:smooth_quartz_stairs":33,"minecraft:oak_leaves":19,"minecraft:white_wool":410,"minecraft:golden_apple":91,"minecraft:dark_oak_trapdoor":1,"minecraft:birch_pressure_plate":5,"minecraft:dirt":6,"minecraft:oak_slab":1,"minecraft:hopper":3,"minecraft:white_bed":2,"minecraft:campfire":5,"minecraft:acacia_sapling":1,"minecraft:gray_concrete":394,"minecraft:black_bed":2,"minecraft:dark_oak_door":3,"minecraft:birch_fence":14,"minecraft:birch_door":2,"minecraft:glass":166,"minecraft:jungle_sapling":10,"minecraft:lever":4,"minecraft:flower_pot":15,"minecraft:sea_lantern":11,"minecraft:firework_rocket":29,"minecraft:lantern":22,"minecraft:grass_block":123,"minecraft:birch_sapling":4,"minecraft:spruce_trapdoor":14,"minecraft:dark_oak_slab":32,"minecraft:diorite_wall":3,"minecraft:tropical_fish_spawn_egg":42,"minecraft:dark_oak_button":2,"minecraft:spruce_sapling":6,"minecraft:gravel":116,"minecraft:stone_brick_stairs":242,"minecraft:barrel":11,"minecraft:stone_bricks":801,"minecraft:item_frame":7,"minecraft:diamond_sword":10,"minecraft:green_carpet":20,"minecraft:birch_button":11,"minecraft:birch_trapdoor":5,"minecraft:dolphin_spawn_egg":7,"minecraft:magma_block":105,"minecraft:black_stained_glass":66,"minecraft:salmon_spawn_egg":23,"minecraft:oak_sapling":73,"minecraft:dark_oak_fence":37,"minecraft:gold_block":7,"minecraft:oak_boat":3,"minecraft:sea_pickle":4,"minecraft:egg":13,"minecraft:white_concrete":975,"minecraft:dandelion":1,"minecraft:bone_meal":704,"minecraft:dark_oak_sapling":5},"minecraft:dropped":{"minecraft:water_bucket":1,"minecraft:bread":1,"minecraft:cooked_chicken":3,"minecraft:chicken":1,"minecraft:cookie":4,"minecraft:birch_pressure_plate":1,"minecraft:lantern":1,"minecraft:tropical_fish":9,"minecraft:chicken_spawn_egg":1,"minecraft:grass_block":1,"minecraft:cod":2,"minecraft:gray_concrete":7,"minecraft:dirt":1,"minecraft:birch_trapdoor":3,"minecraft:mutton":2,"minecraft:acacia_fence_gate":2,"minecraft:sunflower":1,"minecraft:birch_button":14,"minecraft:glass":1,"minecraft:paper":1,"minecraft:trapped_chest":1},"minecraft:custom":{"minecraft:interact_with_furnace":4,"minecraft:mob_kills":1,"minecraft:interact_with_anvil":1,"minecraft:inspect_hopper":11,"minecraft:traded_with_villager":3,"minecraft:open_barrel":96,"minecraft:play_one_minute":771723,"minecraft:pot_flower":13,"minecraft:leave_game":12,"minecraft:time_since_death":14593,"minecraft:climb_one_cm":42752,"minecraft:time_since_rest":14594,"minecraft:walk_one_cm":1831242,"minecraft:damage_taken":8311,"minecraft:sprint_one_cm":1054739,"minecraft:damage_absorbed":760,"minecraft:trigger_trapped_chest":11,"minecraft:drop":56,"minecraft:damage_dealt":540,"minecraft:talked_to_villager":6,"minecraft:swim_one_cm":135885,"minecraft:fly_one_cm":5108887,"minecraft:player_kills":2,"minecraft:open_chest":3,"minecraft:crouch_one_cm":16415,"minecraft:deaths":24,"minecraft:sneak_time":26109,"minecraft:walk_under_water_one_cm":388286,"minecraft:boat_one_cm":3264,"minecraft:aviate_one_cm":885982,"minecraft:jump":3542,"minecraft:walk_on_water_one_cm":50795,"minecraft:fall_one_cm":18032},"minecraft:picked_up":{"minecraft:chicken":1,"minecraft:tripwire_hook":1,"minecraft:water_bucket":1,"minecraft:filled_map":1,"minecraft:birch_planks":1,"minecraft:gold_block":1,"minecraft:birch_button":14,"minecraft:stone_brick_stairs":1,"minecraft:cornflower":1,"minecraft:gray_concrete":2,"minecraft:dirt":2,"minecraft:paper":2,"minecraft:lantern":4,"minecraft:birch_pressure_plate":1,"minecraft:item_frame":1,"minecraft:glass":1,"minecraft:apple":1,"minecraft:stone_bricks":1,"minecraft:sea_pickle":1,"minecraft:acacia_fence_gate":1,"minecraft:cooked_chicken":3,"minecraft:birch_sapling":2,"minecraft:dark_oak_stairs":1,"minecraft:egg":1,"minecraft:stick":8,"minecraft:birch_trapdoor":2,"minecraft:dandelion":2,"minecraft:gravel":3,"minecraft:cookie":3,"minecraft:grass_block":2,"minecraft:trapped_chest":1,"minecraft:green_carpet":11,"minecraft:tropical_fish":9,"minecraft:end_rod":1,"minecraft:oak_sapling":1,"minecraft:mutton":2,"minecraft:dark_oak_fence":1,"minecraft:cod":2,"minecraft:sunflower":1}},"DataVersion":2230}